{
  "creds": {
    "noiseKey": {
      "private": {
        "type": "Buffer",
        "data": "oA0fz2sskkvLNkShDY95FzFSzuscQ/WA+OpBhFxCtUE="
      },
      "public": {
        "type": "Buffer",
        "data": "c6Ozum+EfQDlPWt32t5mEguTTNsOg66yZfhEihdBC2k="
      }
    },
    "signedIdentityKey": {
      "private": {
        "type": "Buffer",
        "data": "eAr7yc80XVdLJWfwHegr0ZHWb+xPwwwIStp2011y0E0="
      },
      "public": {
        "type": "Buffer",
        "data": "oL0XrQrhmtexzvNw9dZFbeizCLb/FSusM2dqlbLP2gY="
      }
    },
    "signedPreKey": {
      "keyPair": {
        "private": {
          "type": "Buffer",
          "data": "+M/IJLCMAy2dQHi+lZG208YAoAqui/EzuAtYoNKbfU8="
        },
        "public": {
          "type": "Buffer",
          "data": "HGO/+N32ZLBK2p6USInAJcVOsie+8tlDv2s4N504hjM="
        }
      },
      "signature": {
        "type": "Buffer",
        "data": "74yBp00X3ETBs2moVvLJkBuDr1vpE9E3qbS4lRuVU1jBKat+bw6QtOyCUW5P5gkPzO9JmZmNCsfri69Tn7BHDw=="
      },
      "keyId": 1
    },
    "registrationId": 35,
    "advSecretKey": "OZWQ5n/9xBDj3YOqxQZLwT8/osOolrgQLT7HXhpdwtM=",
    "processedHistoryMessages": [
      {
        "key": {
          "remoteJid": "6285607959390@s.whatsapp.net",
          "fromMe": true,
          "id": "6E9BF3F937E1C22713F6F1DC8D9AC601"
        },
        "messageTimestamp": 1674057057
      },
      {
        "key": {
          "remoteJid": "6285607959390@s.whatsapp.net",
          "fromMe": true,
          "id": "BB4A3A31FD0A9D25C33EBC2FDDDCE974"
        },
        "messageTimestamp": 1674057057
      },
      {
        "key": {
          "remoteJid": "6285607959390@s.whatsapp.net",
          "fromMe": true,
          "id": "31489CEBAFA46CC4F5CAE6D8D330F9A5"
        },
        "messageTimestamp": 1674057070
      }
    ],
    "nextPreKeyId": 31,
    "firstUnuploadedPreKeyId": 31,
    "accountSettings": {
      "unarchiveChats": false
    },
    "account": {
      "details": "CK3F4f8CENuqoJ4GGAM=",
      "accountSignatureKey": "ELsOElvK685B75wU/AUoySPjqh591sSzpQ+T7xq/f2w=",
      "accountSignature": "XhFatbczK4/MoFcDXkoCUsOeY1ZKiqJQVUTw2QLABzacX68DzQUhdSyGypIOwurB+05+OrkuneVvdSyPxuhjCA==",
      "deviceSignature": "zrVN+SrexBx1Wo/EgKL73bYKG5FcSspIizEsKF82zrMsN2rFa1hKKnu43WDfQCaFnzXTia6rOlTsg2lTJimtCw=="
    },
    "me": {
      "id": "6285607959390:5@s.whatsapp.net",
      "name": "."
    },
    "signalIdentities": [
      {
        "identifier": {
          "name": "6285607959390:5@s.whatsapp.net",
          "deviceId": 0
        },
        "identifierKey": {
          "type": "Buffer",
          "data": "BRC7DhJbyuvOQe+cFPwFKMkj46oefdbEs6UPk+8av39s"
        }
      }
    ],
    "platform": "android",
    "lastAccountSyncTimestamp": 1674057055,
    "myAppStateKeyId": "AAAAABnx"
  },
  "keys": {
    "preKeys": {
      "1": {
        "private": {
          "type": "Buffer",
          "data": "iDbHmUSEQE2NWoDjuqvtAew21Bnq4NTdNuZO628NWkg="
        },
        "public": {
          "type": "Buffer",
          "data": "lYVfGUm3DdZz65adzi7/23XD+WbfaCL0dML7e+DdP3g="
        }
      },
      "2": {
        "private": {
          "type": "Buffer",
          "data": "aEqw5RutHQGfMKg0ulpTpUlcc4Vy8gRMXfVYNMdeKEE="
        },
        "public": {
          "type": "Buffer",
          "data": "aHzwwC8CpJjeNsz1lmkMOl+2mKf4F+Dz7r6xJCRPxkg="
        }
      },
      "3": {
        "private": {
          "type": "Buffer",
          "data": "OGs42m6o3lwlNEqwvncmXtTlkKLmp+aw4Mu4ikQaZXI="
        },
        "public": {
          "type": "Buffer",
          "data": "u7jcgp7C70vDtuR4dKf/KIO+ZBFfU6d0oUmJhDrFaUs="
        }
      },
      "4": {
        "private": {
          "type": "Buffer",
          "data": "6BraFmDxyfo3/ixXbBbahTtpIWmvFTUdbfSH6NX980c="
        },
        "public": {
          "type": "Buffer",
          "data": "5H6JQTp6oIVu+7hryteUw8ysn+Zekwt/4Q/MCXrFhXQ="
        }
      },
      "5": {
        "private": {
          "type": "Buffer",
          "data": "EELuNvPOD803FOjMq1FerTmqS7ieXLbJ+eG5Qw3nv3c="
        },
        "public": {
          "type": "Buffer",
          "data": "sQ1zG8NQ4f5NFG6qtxL2UX/RnhvpVLsYaw8IafXlgmc="
        }
      },
      "6": {
        "private": {
          "type": "Buffer",
          "data": "EKkE3oeOKRPP6il5m/pHiNR96mcZfBXlm85doS1KqXs="
        },
        "public": {
          "type": "Buffer",
          "data": "EWMQRchZwhqlKQTOlQLOIxUNtBobC48AKTPs+LsWoBQ="
        }
      },
      "7": {
        "private": {
          "type": "Buffer",
          "data": "gMtT+b69gw98njUD4CXxT0dcPMyAlr/yejGCzAu9SUk="
        },
        "public": {
          "type": "Buffer",
          "data": "38Tm7/9HOfBuuAJgHWMlBJPfEw1ofZf1KEpnK02SBG0="
        }
      },
      "8": {
        "private": {
          "type": "Buffer",
          "data": "UFnQKw5/c1GnLNWhBH5AD40GEaiRP4I4DYW8QcdYIXw="
        },
        "public": {
          "type": "Buffer",
          "data": "UCFPdGEl5cKHw2PZ22B2im5io9469b8cCwG9UHDU3yQ="
        }
      },
      "9": {
        "private": {
          "type": "Buffer",
          "data": "+FrULnjgxsZok6du5FCikHZ3buwz6OebpzSublth+FQ="
        },
        "public": {
          "type": "Buffer",
          "data": "BWGIan6WRRYz4Gg3LlLHkf2nuWVWkwWJ3pXoCA7fgF4="
        }
      },
      "10": {
        "private": {
          "type": "Buffer",
          "data": "mKbP0j9iRmOgugXSDynNaOOU56QuhN8DGFjcf3as31s="
        },
        "public": {
          "type": "Buffer",
          "data": "uM1liuR1YbQ5RLn2YtoNxlRb7S+uaVuIvlt3c6bSI0w="
        }
      },
      "11": {
        "private": {
          "type": "Buffer",
          "data": "CBcdyInYc04HCjN0hl7Y+GpPCWypMYjaqSAYFQrksFM="
        },
        "public": {
          "type": "Buffer",
          "data": "6RDZuD805PI87PBaASHKy72BKSuc6IZctTcibqvEMkw="
        }
      },
      "12": {
        "private": {
          "type": "Buffer",
          "data": "IFnMSy5CYeGbXeRJEA0VIOPl7ufv+Z65tQnRSTQ+OFE="
        },
        "public": {
          "type": "Buffer",
          "data": "u1CLkDnF6i3asXdHlsnr4DVqQY5nuSl82HbW+7T0Om8="
        }
      },
      "13": {
        "private": {
          "type": "Buffer",
          "data": "KNryhWCy2KHGNA1r9D43wanWFahWK6/ixiT10pEyIWY="
        },
        "public": {
          "type": "Buffer",
          "data": "zwRuIlFfAD3e38Eu07Scw0fxU++f+Af0abHDV5BGeHQ="
        }
      },
      "14": {
        "private": {
          "type": "Buffer",
          "data": "QAdnHVaMbcC+2Iuq56//rfrQ3vjQTb2jEHB263NixWI="
        },
        "public": {
          "type": "Buffer",
          "data": "33qMxWFkLB687+2bcaehe6B2VpjZtJzM6UR0MQNlYCQ="
        }
      },
      "15": {
        "private": {
          "type": "Buffer",
          "data": "iIulr2lEaTiLQ/0EdIR1xwjlKtCqyIVGLWM7wIc1Plg="
        },
        "public": {
          "type": "Buffer",
          "data": "nL7st3qaVtHDoo6uNhf9Ucj/iaBlY1FXBqMix1bit3o="
        }
      },
      "16": {
        "private": {
          "type": "Buffer",
          "data": "6J1uvjsxo1rBHeLvDcE12ES8JOziCxeztwAB28H+3Xw="
        },
        "public": {
          "type": "Buffer",
          "data": "4JrRccXupmNHrCk/Aqd9aqfww4lXRD3gxrU7OctRJw8="
        }
      },
      "17": {
        "private": {
          "type": "Buffer",
          "data": "6D5iOgRdPQB7QWWZ3bklc8U6mopJOSlw2CfznynpSmU="
        },
        "public": {
          "type": "Buffer",
          "data": "590dAr8fIjfRJj8QjIH/iVsxmlvnvZpwYc7hEID1JXo="
        }
      },
      "18": {
        "private": {
          "type": "Buffer",
          "data": "qNYx2cKmGkTsqiglcS8vsngZKvgA3EasJk/fk+fjvl4="
        },
        "public": {
          "type": "Buffer",
          "data": "N9nS/n/2KkSQbtcxfd6atibjSdduSYKrlwtPNB3qEww="
        }
      },
      "19": {
        "private": {
          "type": "Buffer",
          "data": "aMkWsvFN9iGjGH9pDv1cf3hHc4MPO5ScPc01dqG0HUg="
        },
        "public": {
          "type": "Buffer",
          "data": "bqTBgd8yUkiMDq9eEftRo75PcOGEpKAelw+2r+0xlH0="
        }
      },
      "20": {
        "private": {
          "type": "Buffer",
          "data": "4HSoTHkjnOGtEicXnGz1sFUL6ak1L+awW7o1nSnhe1k="
        },
        "public": {
          "type": "Buffer",
          "data": "GR3PWj7ejwvMpfXi+BrDJNH+afxhXHdlPv0U5yYueS0="
        }
      },
      "21": {
        "private": {
          "type": "Buffer",
          "data": "QNhwyRiV+E6OHd7eGWOL2iMKYl9XIi7aRxT6qCdsPE8="
        },
        "public": {
          "type": "Buffer",
          "data": "VOE7x++onP3W05sOCscHOIUGHtppNv+bUYyCCJUYHyU="
        }
      },
      "22": {
        "private": {
          "type": "Buffer",
          "data": "0O4D8xaxDZh44jBlnyTtGWc6tgelGwMEEc8qSVuqTG4="
        },
        "public": {
          "type": "Buffer",
          "data": "/TpLc/QRx6NaWu4ZE6Tpo+VGo3P/xpzpIZ5P4uaI6iw="
        }
      },
      "23": {
        "private": {
          "type": "Buffer",
          "data": "0KW10RFiYqZ5n/rUhqDMcuGToW9QPL2IhI+SHf9p91s="
        },
        "public": {
          "type": "Buffer",
          "data": "Q9MnboMjZ8NhZ/nn8CXk71P8PsmxIc5hA95Z7qNf0SQ="
        }
      },
      "24": {
        "private": {
          "type": "Buffer",
          "data": "SCLbWKthKqCc1DJFagwO1F+uXvZDvCUsPFQ83OLSJHQ="
        },
        "public": {
          "type": "Buffer",
          "data": "vLCCE/cBflYDLEuvT+AGH1qdY3h3E9A+UZlqDGj1yQM="
        }
      },
      "25": {
        "private": {
          "type": "Buffer",
          "data": "SNOq+eAPZEAbPif9Qf14er8fe5WRpQUitJhDZ1qksE0="
        },
        "public": {
          "type": "Buffer",
          "data": "RYHyDyOCdWBcsf6qAsf2+OaPy3+O1VOMmR8vTb0nBi0="
        }
      },
      "26": {
        "private": {
          "type": "Buffer",
          "data": "mALVtBYvHPUoeEMNxBiOSEQkT+WdMOB6jc13DbBFC2Y="
        },
        "public": {
          "type": "Buffer",
          "data": "syf2JEZFvUB9skKalszhPiJAM0gjHHV3xvhx53gJyx0="
        }
      },
      "27": {
        "private": {
          "type": "Buffer",
          "data": "MNzwJhbxzIyp/hRn8ANnSN1DCS5CffxVUtreGpfCcnA="
        },
        "public": {
          "type": "Buffer",
          "data": "ctAnfGgq8IdzRaCQ5ghGjpNAiDAeHDmASFgznOsVcQU="
        }
      },
      "28": {
        "private": {
          "type": "Buffer",
          "data": "4GCFuOaHrD5U1aM+NLC2iGygUnDEM6O6XEc8lmi8AFY="
        },
        "public": {
          "type": "Buffer",
          "data": "0dbMvTKGch/O7o6/io0QXm2/AvdwIG3EsWriPRgSOTY="
        }
      },
      "29": {
        "private": {
          "type": "Buffer",
          "data": "gMqepmR5f7EYgXyKnGf+6Ea14I9bjsYS5lFQUwV9Gks="
        },
        "public": {
          "type": "Buffer",
          "data": "48nYj2rMmy91T4dY9PPIXJeUiCxKwz24HczvvclqYVM="
        }
      },
      "30": {
        "private": {
          "type": "Buffer",
          "data": "aEKi0JPdD2Y3tQ6oBz6CFZEVk4knDUo0MN6zerskL1A="
        },
        "public": {
          "type": "Buffer",
          "data": "re4jDTubgyd+7aXjexeupvsrNOAQMjzZl5FF7ds1CkQ="
        }
      }
    },
    "sessions": {
      "6285607959390.0": {
        "_sessions": {
          "BZ9dZGJb0nDyFQa0t/3HFLYjjuC8g61THhowi1iNLAN2": {
            "registrationId": 1181617595,
            "currentRatchet": {
              "ephemeralKeyPair": {
                "pubKey": "BWLVGPEdnUpM8BA4JO1aYe2iFnPiGcNqIv9LuLi/MZEZ",
                "privKey": "wLlzVQuBwNXpzlwismHw/CwvpFaa8f6ktQVcw79qvF4="
              },
              "lastRemoteEphemeralKey": "BbXoUOPtDOXtGIJypRBjxZVBu4vuPZwjlNSwFdbMszYY",
              "previousCounter": 0,
              "rootKey": "4IlMdyMdFzHADW81l/gIVy6Ji6zqAg2F/qQaxpeTpcs="
            },
            "indexInfo": {
              "baseKey": "BZ9dZGJb0nDyFQa0t/3HFLYjjuC8g61THhowi1iNLAN2",
              "baseKeyType": 2,
              "closed": -1,
              "used": 1674057057149,
              "created": 1674057057149,
              "remoteIdentityKey": "BRC7DhJbyuvOQe+cFPwFKMkj46oefdbEs6UPk+8av39s"
            },
            "_chains": {
              "BbXoUOPtDOXtGIJypRBjxZVBu4vuPZwjlNSwFdbMszYY": {
                "chainKey": {
                  "counter": 6,
                  "key": "CoNzHyZ5kg2QybuoA1yacBCpyv/DhxMInjqJRpWyt9o="
                },
                "chainType": 2,
                "messageKeys": {}
              },
              "BWLVGPEdnUpM8BA4JO1aYe2iFnPiGcNqIv9LuLi/MZEZ": {
                "chainKey": {
                  "counter": 0,
                  "key": "R/EHFZR8HXiWt/PLVrmNpIrXs/w7vIbJHF02dyiGEwg="
                },
                "chainType": 1,
                "messageKeys": {}
              }
            }
          }
        },
        "version": "v1"
      },
      "6285607959390:3.0": {
        "_sessions": {
          "BYkV0s2Q9Lew83zLCSTHeA9FaWgEt0zDSr624OiKmAoJ": {
            "registrationId": 153,
            "currentRatchet": {
              "ephemeralKeyPair": {
                "pubKey": "BfTp8IXeOrRlAn2ZP4mnJEBL2U3yqLJHXjrmWSyP8CA/",
                "privKey": "6Jsf2y049Qupvu18Esef/CbuOJ35eGL6paCKIv+kW3M="
              },
              "lastRemoteEphemeralKey": "BZbxZGmEaFFsXwqHfoCAlp06xEX58DMGHhZLj22J3Toj",
              "previousCounter": 0,
              "rootKey": "CBub+2uofOZtEYXkFfEPyZMreJ+d4DmTz725Sxjka80="
            },
            "indexInfo": {
              "baseKey": "BYkV0s2Q9Lew83zLCSTHeA9FaWgEt0zDSr624OiKmAoJ",
              "baseKeyType": 1,
              "closed": -1,
              "used": 1674057075222,
              "created": 1674057075222,
              "remoteIdentityKey": "BdA/Uuw2EQ6QTM/iTnT8wejd37YSR/xHRz/DbCOuYC5A"
            },
            "_chains": {
              "BfTp8IXeOrRlAn2ZP4mnJEBL2U3yqLJHXjrmWSyP8CA/": {
                "chainKey": {
                  "counter": 0,
                  "key": "gcG+VYp/QuD62TKlktApW/v/klniyUwypwLMXt9wewc="
                },
                "chainType": 1,
                "messageKeys": {}
              }
            },
            "pendingPreKey": {
              "signedKeyId": 1,
              "baseKey": "BYkV0s2Q9Lew83zLCSTHeA9FaWgEt0zDSr624OiKmAoJ",
              "preKeyId": 1
            }
          }
        },
        "version": "v1"
      },
      "6285607959390:4.0": {
        "_sessions": {
          "BURxcm2xM9tbOTDSVQ7oZYjNk3neLOf2Ub3pWXC4p2QL": {
            "registrationId": 122,
            "currentRatchet": {
              "ephemeralKeyPair": {
                "pubKey": "BTmx+oUX0iE4yAHdUSn9MTONpzivVXZAGJNOsPLNr5hf",
                "privKey": "+AbAlkNersn+k7HlVM2njcihh1+h1l7sTj1LS2SVwk4="
              },
              "lastRemoteEphemeralKey": "BVKTQOfCkqyVJK7cKnpF/TAFs5p+6dqA66iNeHT9xihc",
              "previousCounter": 0,
              "rootKey": "cIZDXXsp7fR0F5j6gWfPVpAdBr1IZVA67anh5zh1NEk="
            },
            "indexInfo": {
              "baseKey": "BURxcm2xM9tbOTDSVQ7oZYjNk3neLOf2Ub3pWXC4p2QL",
              "baseKeyType": 1,
              "closed": -1,
              "used": 1674057075249,
              "created": 1674057075249,
              "remoteIdentityKey": "BQZ88Lw/9a0kpK4hQ+ye0lvkAlBt7LP/qB4JRVDvRWk3"
            },
            "_chains": {
              "BTmx+oUX0iE4yAHdUSn9MTONpzivVXZAGJNOsPLNr5hf": {
                "chainKey": {
                  "counter": 0,
                  "key": "DSYbqx8ntaFlHt/tuORZt+D0mg51R2ypu3V22Hgc4VA="
                },
                "chainType": 1,
                "messageKeys": {}
              }
            },
            "pendingPreKey": {
              "signedKeyId": 1,
              "baseKey": "BURxcm2xM9tbOTDSVQ7oZYjNk3neLOf2Ub3pWXC4p2QL",
              "preKeyId": 2
            }
          }
        },
        "version": "v1"
      },
      "6285812373011.0": {
        "_sessions": {
          "BYclJCwf33yHV+F6ZccGMoJNKB0jlK7UHyD3AjqTLM1d": {
            "registrationId": 1372011052,
            "currentRatchet": {
              "ephemeralKeyPair": {
                "pubKey": "BRwx4y/ooPGMviSSMl4OPByLTgD/p3lqtSQZ3FDQfVZs",
                "privKey": "SNJPaHzlPOp648TgDpuP5vhwImzMQc9hkQYHLF7fLFg="
              },
              "lastRemoteEphemeralKey": "BSu3tzW9jOL78uBoCGYjZixZquLAZ8ndjUNpGwtxxI4a",
              "previousCounter": 0,
              "rootKey": "Whii0kTpK1N5hY5kV7oEieJ4FuuWwWXgUHcewQGJO3Q="
            },
            "indexInfo": {
              "baseKey": "BYclJCwf33yHV+F6ZccGMoJNKB0jlK7UHyD3AjqTLM1d",
              "baseKeyType": 1,
              "closed": -1,
              "used": 1674057075275,
              "created": 1674057075275,
              "remoteIdentityKey": "BdTru5ruDIdbpRN1qnP52FwOVBXDu8oLb8WBasgAzi5l"
            },
            "_chains": {
              "BRwx4y/ooPGMviSSMl4OPByLTgD/p3lqtSQZ3FDQfVZs": {
                "chainKey": {
                  "counter": 0,
                  "key": "dDYVjNp7RJg8RWpdUMiWHYUOn0m0Gobgy09OXb5cXc0="
                },
                "chainType": 1,
                "messageKeys": {}
              }
            },
            "pendingPreKey": {
              "signedKeyId": 3,
              "baseKey": "BYclJCwf33yHV+F6ZccGMoJNKB0jlK7UHyD3AjqTLM1d",
              "preKeyId": 12009913
            }
          }
        },
        "version": "v1"
      }
    },
    "appStateSyncKeys": {
      "AAAAABny": {
        "keyData": "7TEBeMko8oBZyvnKGlgbKgAvEFwjQtsG/HgQ+8LpWoY=",
        "fingerprint": {
          "rawId": 804807340,
          "currentIndex": 2,
          "deviceIndexes": [
            0
          ]
        },
        "timestamp": "1674029821424"
      },
      "AAAAABnz": {
        "keyData": "ldme9zbgTQ0zJAYb86wmYmrgwczDGxNw6VZP1WTntiY=",
        "fingerprint": {
          "rawId": 804807341,
          "currentIndex": 1,
          "deviceIndexes": [
            0,
            1
          ]
        },
        "timestamp": "1674030634543"
      },
      "AAAAABnw": {
        "keyData": "g3xFoSpqQXWwJEKQ8Cx9iXNn0g0plTEtl+e0ooMmtKI=",
        "fingerprint": {
          "rawId": 804807340,
          "currentIndex": 1,
          "deviceIndexes": [
            0,
            1
          ]
        },
        "timestamp": "0"
      },
      "AAAAABnx": {
        "keyData": "AbuTUBFXg0ytstyLUaDonjJxfgyEeIACdB3XFSCzTYY=",
        "fingerprint": {
          "rawId": 804807340,
          "currentIndex": 2,
          "deviceIndexes": [
            0,
            1
          ]
        },
        "timestamp": "1674028385411"
      }
    },
    "appStateVersions": {
      "critical_block": {
        "version": 3,
        "hash": {
          "type": "Buffer",
          "data": "+5RY719cTruPeVMGB7Ue/tDAkGT9ZYtIXw+GKZVuqkxIuAXfgD6M+0NoK8hFAOHNC/J3vlYpycA2EQLTUnU2b9ERoM8Kg8j48M6aMUB0Xe/49KwOe7U3fjffTFwNykPnb1Qokg8jpnfrrWKt+6MF6tKiZKDMKX20XEV28SRA2fA="
        },
        "indexValueMap": {
          "6Iu5dWz69vYp1nHffX8G7+e8RBzwk49U5yfVzJZKPSQ=": {
            "valueMac": {
              "type": "Buffer",
              "data": "VHngnpDK/N4xVa74uUYe9zxS8nYZHzz2aINiKOsqVDk="
            }
          },
          "736y4jXC8uAk3bi+QuRtNDSp55YfSJGFG7lBSfq0p1c=": {
            "valueMac": {
              "type": "Buffer",
              "data": "HI4sUmIgrTfrvps/2LWA+QxEsmSd17vjj8LBaV/EQiY="
            }
          },
          "DXDh8NKvE5AOkhtAKW/u259vN1GCLKt0RTF7hr+fsDg=": {
            "valueMac": {
              "type": "Buffer",
              "data": "MVYw2ro9Xtv5braPH/miTTImTc95oi7JOWwnBO1Uy4c="
            }
          }
        }
      },
      "critical_unblock_low": {
        "version": 12,
        "hash": {
          "type": "Buffer",
          "data": "27x0X3bGVNbe8V7VP3hILgIYblYjEnUA/+Azfhh9hTicWTXONai9MP6+nRCK8aW1Yq6Sdsqsryex5JaJn/un3oGwsfgxbcFPuJ5gGFeioyOMqTMennhK4SoXdKK0BdZXff9AksM0MyC76WxJSgsHpwCIxkf3kyFVnG4CYcTIBf0="
        },
        "indexValueMap": {
          "vt9k7aKw/ayg9qc7M0gRdYEgW+wwmzzr28UKJiFEum4=": {
            "valueMac": {
              "type": "Buffer",
              "data": "OweVzfgUmWUBKogA2tZa3tH+Ny4bB6rqSHXMSbUG1OA="
            }
          },
          "9Xp5wi+aY7SAD8LN6ZuvCx7mP5BCJMlpjv99LfpcBIM=": {
            "valueMac": {
              "type": "Buffer",
              "data": "qSW3h5xvnMaoC/TMUqODMn0jBX+h4LBE6k4mDLah008="
            }
          },
          "T3dUyxLjHNQ7xECOYQI/sPNlbmEk9BRXRwDdO6Vf8jM=": {
            "valueMac": {
              "type": "Buffer",
              "data": "/SImX2xbbN85wKKYsU+FOvI8BifO7TJGXkkRbWy0p8Y="
            }
          },
          "/p5842/EJPZY3sgdPZePZRQmECUj6FW2FTTvMAk1Wdw=": {
            "valueMac": {
              "type": "Buffer",
              "data": "a4OwC3eH7tiNDwy1Yd4L0cC2DgV6Ah+5Sj8UXDHdZe0="
            }
          },
          "SWpZNy7Amul0qIDov3AozQY7/rUxYEjH0Qi7KKm2NS0=": {
            "valueMac": {
              "type": "Buffer",
              "data": "2R8xfolHI06AP47AtZvzRNnSuKyo6qm+LwXw/zMGTFE="
            }
          },
          "KQ2hKmDhsHrWTL5gMPd1v9eZo4XhrcJcGneU8xdwgHE=": {
            "valueMac": {
              "type": "Buffer",
              "data": "WgWsfWNa0u6W4BsxQ7yjE344NpVJ+Puk4Lk4Zhfm2so="
            }
          },
          "jcmSw4xZrLfXFHL8rdHM7ZvifsrjqdeqCkl+7Sp3MUg=": {
            "valueMac": {
              "type": "Buffer",
              "data": "eMoqPxPzoBVmAxHxHdboj7GJDkkS/MCQgU2fdVu7/k8="
            }
          },
          "8BC+xbv5rQXZC8GBGMcR+rrcLWMQsS4DnvTbulxo8qs=": {
            "valueMac": {
              "type": "Buffer",
              "data": "j0uLCuKh5cDMKi6jFhCtkwoHs9Z6ZyMVaQjE2w2sTNk="
            }
          },
          "7TYmzu42KDomFCgWLDwnVIywgjPVBSfq3r17ZtHQ+i8=": {
            "valueMac": {
              "type": "Buffer",
              "data": "cc+gzq1vgCSJaVE7URNnqc6boH3kfd/q0LlbOU2Tp24="
            }
          },
          "8EFczgKaxVBASS8HNCCi+mcGD5yLwE2Glu83HPqfj0U=": {
            "valueMac": {
              "type": "Buffer",
              "data": "vEPkqIk7K7fWd4Ph0vlxxzuV1YYoURDVPT0v5WsdMhU="
            }
          },
          "zpIIBnlQGq4Y8A/cdvie6iDFFs0P6VCmgoMqusHZu58=": {
            "valueMac": {
              "type": "Buffer",
              "data": "70bzdEA0ZnH565+szkxTQDDZNbT1b9yRMYoEzFDhoOw="
            }
          },
          "n7FtjpqOtbUQ4bu3ryTLmMGx941v3wxP0W0qoewHQ5w=": {
            "valueMac": {
              "type": "Buffer",
              "data": "puX81wgtPXQjMV3ABuqF1kmrpuyOmO5KdY2FKzOyJ/o="
            }
          },
          "8MhVOUN54/1/f0cwMz6LorUKD5TM54tkhJbKVRkzmS8=": {
            "valueMac": {
              "type": "Buffer",
              "data": "ft1SJPCdiZOpK+uZ7bEiMZyJK5zRr3uWQoussHmx0oI="
            }
          },
          "kJyPwq8WswgIQlruJbzqy8NODKkggm8KnRQq+QsabIs=": {
            "valueMac": {
              "type": "Buffer",
              "data": "OJdPNAV2fJr1mr+Lt4z6DGaAIizZ7D3qu31NdgxWwXE="
            }
          },
          "M3WQ/xvzzpT48Bm7SwrnPHHGpJEeu6C1KRhunHU1Ufw=": {
            "valueMac": {
              "type": "Buffer",
              "data": "vBuCgvXoBxwTQInHpeOWhI43gFpHGOusehjM45Xk+EQ="
            }
          },
          "stTvESQjg6GQkHDaR/+93lPEkIRXJ9UEsj2K5/Kb/OY=": {
            "valueMac": {
              "type": "Buffer",
              "data": "GC6m2N6rlOXQaka689s0v2AVbwQFMB1cl31MtH8qsqo="
            }
          },
          "3wFd9DDN/h4S1np6XeAsoVDthlTmrtMzDdJfWg2+DoA=": {
            "valueMac": {
              "type": "Buffer",
              "data": "PtD824p9eOdbdpfyhC8dwhZSZXBfTkyoag5Xa/PMUKE="
            }
          },
          "WpyBE4twB8D2DFrV/IBvesPNQtUGVf0XeMPbY/GGv3s=": {
            "valueMac": {
              "type": "Buffer",
              "data": "sQHTDAWBKqFX0b+FIzkdPNw80srEEDUemMXydeLeOJI="
            }
          },
          "yyeO1CWvkes2BYDkIjpmu1c43W0dDPTUBU2y5c31sqM=": {
            "valueMac": {
              "type": "Buffer",
              "data": "zIqnBABEPOqfi6ydoQ7e+bObKuAFrhQN/XQltvdvC6M="
            }
          },
          "3yKNXrKerCX51vF9jUgtyKxUTNkCcmfuw+ObK/7n/f0=": {
            "valueMac": {
              "type": "Buffer",
              "data": "aqHRkEf1S4HAykLevZL/V/mQtxP1efre3pHu+I/XGnw="
            }
          },
          "PzKDN9AQdKtGdrNiZBn+JPKQY/TBJuVovFvrq1v/iv8=": {
            "valueMac": {
              "type": "Buffer",
              "data": "HhhpxJ7y9uBUYA4s3GxF1YLR5NzQIshNEDsJyoU6eZc="
            }
          },
          "uBjUkV5+gL9uEBJISQyzhn9nJnHIXwiHVV0l2Pr/Wew=": {
            "valueMac": {
              "type": "Buffer",
              "data": "oaNfxRHynuM9COCibgNHUlwhNEqgzpXvRUGOJgEmfvM="
            }
          },
          "ghdyDeVoh0JENIWlclPbXRkc3tqfo+zLQoyvn6Wjqwc=": {
            "valueMac": {
              "type": "Buffer",
              "data": "PfAccE1xL4EcTiDwub/ComPreiDxgCsRtPxitLzZtLU="
            }
          },
          "RUdvm+L7imiaZrWJk9ySUl8lXvsbaBARF/whdwZGuSo=": {
            "valueMac": {
              "type": "Buffer",
              "data": "0HGKxCqr0qM2zCGwyIC3rQ8cceTTIgI+EbMDZ2UT6Us="
            }
          },
          "Ec9TXf8hAHOc9+Y/O+tjrM6EdNjZna5a184Z9jJrYsU=": {
            "valueMac": {
              "type": "Buffer",
              "data": "CVok0HD9DchPe7LrOsiUE6t0zqgKjIgQ6Y8fBnLtfdA="
            }
          },
          "4lJEnCUMpxSjF/Vg9hCNgwYQLv4I+MGvnhkp23kqf0w=": {
            "valueMac": {
              "type": "Buffer",
              "data": "JXvE30PnNM1AjlQMSeBsFJvtlL+sOdYHrAcNz9RsW+U="
            }
          },
          "hu8zXw11sWl7BKlrsTQDEQZtHxeSLR8vwkmgM+J5F2A=": {
            "valueMac": {
              "type": "Buffer",
              "data": "RO+CNC+gTX5Mz7wYsalatN/YJhBrdQGhi1pRSNJOIOM="
            }
          },
          "a2AtwEHzQoJzlwxriKUc9J5kHeoSGjZ1xtibkHbPY9s=": {
            "valueMac": {
              "type": "Buffer",
              "data": "ZD9nqqy5zhpysmZkymOuox1dmYxDh9LtZFrTU4ZJJZA="
            }
          },
          "ALCEdapEGei7TRuoCSKsbJk+41bH/rHJrnxjxbCy6s0=": {
            "valueMac": {
              "type": "Buffer",
              "data": "Lkronn6yyyaGLJGYSmJN3hDRENLAxC2Bs8LH2Mw/nOY="
            }
          },
          "Vte8eEv6huxvX5rV+8kIga+/BY0KSw+kCUTpmUKJdtw=": {
            "valueMac": {
              "type": "Buffer",
              "data": "+z93Zh8GoUV/OVJVbKDSn/UTxM4KnIrmJ268F7GqtLs="
            }
          },
          "ymWwmLHfG66zl/fIVpDUhT3ioHOcBuaAAXrjGY2x6GU=": {
            "valueMac": {
              "type": "Buffer",
              "data": "HCzwfxG9sKfN+MI+Of8OYGSpsR+n35Y+QhOvgrz9BaE="
            }
          },
          "hwbzdMCA6aDqMIqx72xmSQwVXc2yCVa1vcNxa1FUH6k=": {
            "valueMac": {
              "type": "Buffer",
              "data": "efac/BU/qz5jynBa/rrCVCPztCe6JOZNm40gNAu57bE="
            }
          },
          "kkyVcpTCYwWnKi0snk3qyGGBDx+VnkVTRqeYEzz5stw=": {
            "valueMac": {
              "type": "Buffer",
              "data": "J7B3HW+rPjJykaL45j5pwHT190lD9DnDgRoo8lR/4WU="
            }
          },
          "R+nb7CPYlgLCMclI46D5FT3KoOPiGmunD1xyIbnDMJc=": {
            "valueMac": {
              "type": "Buffer",
              "data": "ZvfoUb9IBeUrqsuaC8W5Yr3h8r13wss7gMGDzyX3jS0="
            }
          },
          "3o2w8+2tnlc17gy7YcMOCfRT//QxiD/4Y1VL7znKGXM=": {
            "valueMac": {
              "type": "Buffer",
              "data": "BGDMSK5LZ/Jf7Ui+S8ac1J2WAuHcZ3ptbiZj6+i+gC4="
            }
          },
          "XtrcGV5QcIyNdBuwS2fN4GgRCAsDZ7Bo1j4hoJvKvhs=": {
            "valueMac": {
              "type": "Buffer",
              "data": "jUrDPbMyRD5ytI3EerJxpV8fojxZxjGfPHLmD5TlmbM="
            }
          },
          "jIM27L+YVIsbXxwrQQGlUzhgn2Gum/ASzvN6FAx0SrA=": {
            "valueMac": {
              "type": "Buffer",
              "data": "o4EAQoi4JkZRExfu/jci6ubmh+jpJCVJTQ0YOpAypkw="
            }
          },
          "u4P4ed9RBhRgtDRbrru57UZjzWCf6k7qBJHrBNLMxOk=": {
            "valueMac": {
              "type": "Buffer",
              "data": "gDCjadpIwAqbhSob2Hkq/Dg+rgFEl9C2DsxhcJGpCgk="
            }
          },
          "KFyMcJ2dXC3gFJV1HbG93FEf5iOzkUoYXIF1NjtP4+8=": {
            "valueMac": {
              "type": "Buffer",
              "data": "PvjUhycAiqE6XayRK7TSmz+zXVv32A4wD6fdUekFAM0="
            }
          },
          "LCalqrzeW8gvtgRxvR3mGIn1i9dpzDRP2QczKp/0H4c=": {
            "valueMac": {
              "type": "Buffer",
              "data": "HVCmP3MbIKoO3fcoxbkr3HkVvJoKw8QwnKHVN328iNs="
            }
          },
          "IeJcRgEE2ZAZRV8Mi36KKm/TPMfjusZDFz0r+Qf+m2Q=": {
            "valueMac": {
              "type": "Buffer",
              "data": "nbgiXvJgODsWbnXznunaaDheN+5IYUlhe1rTW7rUp8Y="
            }
          },
          "Sz5KzIZiSc8hEw+5OnPXCmeQ5A+rPPSX5eNthZn10Dg=": {
            "valueMac": {
              "type": "Buffer",
              "data": "BavqLevxJSrBfItSHEfHlmuV+oczIKGVeGBWT5fLVTo="
            }
          },
          "kEHHFqeXd3mH9SIkSYkSfU72gxrNygzm0J0/5ShRqsk=": {
            "valueMac": {
              "type": "Buffer",
              "data": "UdcsEW8vyRrBwqmccN9v0PgpL/nGJfxGI6bTYBiKpAw="
            }
          },
          "5QJIktEWm+s56VqPnDl1M//IGmuoW8KK/+5rxTLOo4w=": {
            "valueMac": {
              "type": "Buffer",
              "data": "pk1hiGgIYURh4x3Ej1nNzSbM4F+IttZKE9l2E/1xRM0="
            }
          },
          "a6z345AHMb50+ffye/z/69scoI9/Vt+RMLhKrlTmIdg=": {
            "valueMac": {
              "type": "Buffer",
              "data": "s2s7pDxyqrjTAIEhbGpT3aQGlPnG2pKLeHdP0HHv7+M="
            }
          },
          "6kMbmULaYivtiQRZe8wOav8WXuzsmegpZMsRbHTF/kM=": {
            "valueMac": {
              "type": "Buffer",
              "data": "t9WgipX1lC/tIkUChHtI+n+2c+BYD2LlxaWDevsDgmY="
            }
          },
          "RZNgpGNcqtOF4lmLhg2eBWTg5c9tXynJIhjRsc+OYOM=": {
            "valueMac": {
              "type": "Buffer",
              "data": "9KfWF+9HJ8wmtX9ILpXbpZPdVBuNLLAo92BwJ8piUoI="
            }
          },
          "Ey96DhFagXvVO0/YjJIkrIMcN/nBRKWLn0QPg0s8+Xg=": {
            "valueMac": {
              "type": "Buffer",
              "data": "dSWFFF3TjyBhf6yTvIs8k4rhAuj3JyUHTRngBqHVn/s="
            }
          },
          "Asy+IYkOYC96OK57cCO27Yq2ukvtqo6DNki4y/w6sQE=": {
            "valueMac": {
              "type": "Buffer",
              "data": "FDLpXMaZTLWk22tx2FJ1fICA/fepxto5nqMpg2m9v10="
            }
          },
          "RdK0t3K0AXEP+SZ6kuVGjT0mPbPzue+wJaDjsl9arck=": {
            "valueMac": {
              "type": "Buffer",
              "data": "wteBo+jlFkjqhnNKt/pu1Q0cw/PaFFr5Te9yiaAOdjY="
            }
          },
          "DwoHhXV/1vYQAz7LIqtMp8im4Mc/z158Ld2gg0FD/mU=": {
            "valueMac": {
              "type": "Buffer",
              "data": "5YEZMRL5VxGSsSQ7ODzGqjNuVWdLdea/R4vsR+e6Sz8="
            }
          },
          "uIShelqD/y1VqJduDZoejtqTUgS+XuOZWJ4nwPGMuzU=": {
            "valueMac": {
              "type": "Buffer",
              "data": "QPok0C4yxBK8ak/Ddhlqx0UFP2yJcXHCgkgGAFAJ2gk="
            }
          },
          "pfo8AAb0Cif1G/Uow9Ele0C4JVKQ8kgZQKmMYpCN6/4=": {
            "valueMac": {
              "type": "Buffer",
              "data": "L6AEtFbRn/uBTJaaj3IobCQ+xUT2XPIwrEeDEL6uhAA="
            }
          },
          "/HxMNRyZWsGN6zZ7E4vH4WaY5aTCJLsWF9dunSeWq/A=": {
            "valueMac": {
              "type": "Buffer",
              "data": "xYTbvTL8VaEmUj6r7cnzBTBt3e6v0aLWcIADVsjeX2w="
            }
          },
          "9IXZJOipaDrYS7rY0LtH/7IE+Mckbo/qLMVzUpiZqtA=": {
            "valueMac": {
              "type": "Buffer",
              "data": "4pH8L59jLIB+iquSJX0QDRjxq4aT9+b6tvyp9+bsp0Q="
            }
          },
          "wfXGuRPMTbimXSt90cbudPCOPcnSz/TfO+mhXYBiSGI=": {
            "valueMac": {
              "type": "Buffer",
              "data": "6thcP3Hgxi4cwP438twd3oUJaTWM/n8teijXQU+OqlU="
            }
          },
          "Hv6zc0fa/ACNoKymdyVqyyF/c22LpNn/uv+8Bmm5X64=": {
            "valueMac": {
              "type": "Buffer",
              "data": "OipuGLNEzEug+7S3D3irOBaPBe4UkqUEG9jaRWhPle4="
            }
          },
          "ZFLdErmP8r0Pxk1Q1KI0aMn6hDJoHru0Y+z9O1ZjkGs=": {
            "valueMac": {
              "type": "Buffer",
              "data": "qTwG4nUzoDLDvOV+vmfrWs5qEYt9zzJkUzrzohh7Su0="
            }
          },
          "xDM3A5T5WRXaSebgenB7viTtRbt9xWKQld0YhsO94J8=": {
            "valueMac": {
              "type": "Buffer",
              "data": "/UCdJjUdhSznI7rneGG76MrCZYPA+Enzx1LcN9afy7s="
            }
          },
          "ZicA3EqToGHP34Uu4EceukdYlirWViB70BSnz+A8ElY=": {
            "valueMac": {
              "type": "Buffer",
              "data": "xrSOOsRGEADbYFUxnBk6p3bpjFtVG/NbOTnVDCZJJfA="
            }
          },
          "MROXr2ZCRcsyw4AVuBw5nVAMg497DL4Ilmng9rXXFzc=": {
            "valueMac": {
              "type": "Buffer",
              "data": "JbyeBUUXYhzlfa0QhOtZb2nqIOup+qabIQ526CW039w="
            }
          },
          "5xjFDs+ym+aduwuwt+gqrof5i/Jq2+b+Gd+d/GyLRU8=": {
            "valueMac": {
              "type": "Buffer",
              "data": "qD17q0bq0a0gAapVfX3cnsgoXeILFfUjmC8DPpIIJzw="
            }
          },
          "71DJ9TUOk61NqtO3cQcgP6h9BP6CBpFhPvL3H27uzs4=": {
            "valueMac": {
              "type": "Buffer",
              "data": "lT0nLpuKa3S3t2wxCykTNK3EDvSpF092+oRrwXJlPUE="
            }
          },
          "S4xvfu6zvDFMdmbwpUn1243cC7YxuB7ZACqJI0BAxJ0=": {
            "valueMac": {
              "type": "Buffer",
              "data": "RCptBhGrQXuycC5paFp49kcQI6i2fWCm4yVZuE+tuQ0="
            }
          },
          "vZQNhjLXeRFZhFPqbeumdsF42jg/ej1IsPpvAvKCM8s=": {
            "valueMac": {
              "type": "Buffer",
              "data": "ZwIPMXdijKsP7zMNiQQISLQo1B0yg4DNmN6f7G8zWWA="
            }
          },
          "gzoFDlir+GecxnglVuwdieOl6Oyao8ULGRdwqeU+ppo=": {
            "valueMac": {
              "type": "Buffer",
              "data": "c32N+0vMqypcS6z16qFU2lDjPC44RgygvGgQhMAktus="
            }
          },
          "PnbvX1HLaicW5oIg+7p6rFGi6JbsDyam4Q27jdok794=": {
            "valueMac": {
              "type": "Buffer",
              "data": "L9kuYVeZDPNDaO6RvwSNOfTADSqznLDk4GG3qjKydsU="
            }
          },
          "P3IcrvwIo7bfUQfBeu7hrOVpWIUMMLGabIy9F0LIpRI=": {
            "valueMac": {
              "type": "Buffer",
              "data": "PyvYrFN55q5Tcqo9N5A2uJv/5HyoPrbgcFgo7RhE6C4="
            }
          },
          "lV4vG4x7z4rDjcEEDiIbAt1ciEsKknV6JlVH+2Y4vwo=": {
            "valueMac": {
              "type": "Buffer",
              "data": "aB1NSCFgwgq63jgl1BPcvgb+h38XydJs8wq4aqT8vQA="
            }
          },
          "mOt4KzO20eVixpfo3ysU5ScJ7PFACMZre3SIT1JuguQ=": {
            "valueMac": {
              "type": "Buffer",
              "data": "vTwe3GTqLNTouKkrQvGy8AX6ZEUIqE628FilADagFIA="
            }
          },
          "jZJ52Iq+klq62Si6LggayB0OBzFHiCYs+P4TYg/UsS4=": {
            "valueMac": {
              "type": "Buffer",
              "data": "UmKTizPKNIbyljCXdFao/75bTst0MuRUpTt2VVJPauI="
            }
          },
          "5QZO9oW0gapybiaW7JLUJsZvyIV+wAh8BcH621gdRsk=": {
            "valueMac": {
              "type": "Buffer",
              "data": "3RLUKtTi9o6pLb/mewaHcA8Aikqizey+EhGzoFT8pCA="
            }
          },
          "YdTkDWYXqSGNRCGiwL7kKCOra4h94dwy10H2R+8Z31k=": {
            "valueMac": {
              "type": "Buffer",
              "data": "yBJ6DMX7fRYTmnSY3MMlgC7QmKzBJi4MuPTuf/THRM8="
            }
          },
          "DVB2KN7M8u2yn+fRG7OzyKxoKB+PiOq/MqAzkfSexCY=": {
            "valueMac": {
              "type": "Buffer",
              "data": "59SlhZojQdkuj8U6da3SBSiMrGVK4EP02/HBr9LJdHQ="
            }
          },
          "hLs2tISNKm5SwkVdz9CuqAPGeBbfCPrDq9KajtImnRk=": {
            "valueMac": {
              "type": "Buffer",
              "data": "loVK0Mtf1zdrjLBDgfuKLyPNpaAlYmBCx/eB/01j+q4="
            }
          },
          "Mc8sngJ6TD5TdWEJdUXm5HHLxhDjtwXToDn3COdNwzM=": {
            "valueMac": {
              "type": "Buffer",
              "data": "59d1vBz9RgQzWMVgHRQQ6Q/60ti+PEowCJnUA1iofgk="
            }
          },
          "I18lkz2wafxL6PsxilLxyUqz48nOahAGyGev2HI0FFA=": {
            "valueMac": {
              "type": "Buffer",
              "data": "FB4ltJZw6Sb7TsvEiSQtDJcLhpwnHevQk6aTIrZ9sO0="
            }
          },
          "ZfYl7EpxZmdAYFr3BrVC067MREnHByLM9dM12g/8oG8=": {
            "valueMac": {
              "type": "Buffer",
              "data": "rcXGOnIYmqld/VCsAdbWs+itr5IepXKVXy1h733YcYs="
            }
          },
          "I3zRkcDYmBsGSighgTLQQKnyqOtx3rypqORUgnLQopU=": {
            "valueMac": {
              "type": "Buffer",
              "data": "Dhddjmy8epfFCRwDKGJ69CNFH1cU8sQuCX1gY699GcU="
            }
          },
          "lHWvRz7ib3bRY0z5HqG1Qyk06rBLQOnh7ZNlr+/oFK8=": {
            "valueMac": {
              "type": "Buffer",
              "data": "eSWhvIMXRMMDNFpxvbWjNNysXx51ap4P+x+7rE+4I3c="
            }
          },
          "EIJ2Qbf1BuzYzu2kiBKgf3SAI/pJc+uisQT39oekpoU=": {
            "valueMac": {
              "type": "Buffer",
              "data": "fE2BM/FE1eBkcLtqnbk1vDyeWG0cY35nzet5k+i1DG8="
            }
          },
          "UsWNobtE5sRb4EZBtF1FFW0Mant+eFwPo+u/PQ8MdOU=": {
            "valueMac": {
              "type": "Buffer",
              "data": "fosr1GWEVU1aXOoA2XxzGctXRgPpoa7nJ4Uczy7VDfE="
            }
          },
          "t+L175HZdMOBWUpifB+o2/l1ISg+d1ZPW+crf9IRT0c=": {
            "valueMac": {
              "type": "Buffer",
              "data": "x7QnkAMwYLTz5AEtjkjvjLutf2nQ7FaO4akhRWaWD0M="
            }
          },
          "29NsHpDvmAFn0BzRQgyLTwfZlqP74QoBSl7qzSmqZzU=": {
            "valueMac": {
              "type": "Buffer",
              "data": "xrvVmQa68obM8ifeCbAUmIDS5MWafC/hlM+fj2SYUuQ="
            }
          },
          "o0l66+ePazNVExqXV3NBoFUtriaX9lH7gu9DpyKVHd0=": {
            "valueMac": {
              "type": "Buffer",
              "data": "RvLwJgkJZ272+CVzKjLWvCGqKLc5JBaPlM/iNkymDzU="
            }
          },
          "GyjPYZqF4/9Vp8erdG8LFEQLxXSWF0o0wvpx9pNZq58=": {
            "valueMac": {
              "type": "Buffer",
              "data": "8SlxshbXWuuLQuSEaJwhxW/7abXmlsyH48geNJB7r1g="
            }
          },
          "W2SWGW6sSiqyyeRGXlb0vTzp0CmOSkWJ64hMOf3VoLY=": {
            "valueMac": {
              "type": "Buffer",
              "data": "lu0+1cxh/RUJLomvTEBA1F9wpkg4x7Ap6sm23k9lIhU="
            }
          },
          "gufoCv61ZMcnGEWyVDbCvBg5wZseZeNWVoSx/yUTqh0=": {
            "valueMac": {
              "type": "Buffer",
              "data": "Meh/N374vmt8/h18ysDk9E87x9J9a2b6gsEEtkrFyWo="
            }
          },
          "x0AIvzUnHnK6buCYmb3WJwI9ngc+23q7LXOO5vXgwKM=": {
            "valueMac": {
              "type": "Buffer",
              "data": "qQSltu7nrNov7yIuZIjqnVBxkJDv+y3okrLJJmAa7JI="
            }
          },
          "WkiObdo13B0ymjW9MHYOs33uHndpgLF5FqnA7XqXAKk=": {
            "valueMac": {
              "type": "Buffer",
              "data": "VNz31PIx88Cch++nv+q3h8E/pRR0cyx6IfFVfYN8Tq8="
            }
          },
          "jHS5nYqLNpMSEDQ3yprprQcM9DWkcgCI2Q12sS9HPqs=": {
            "valueMac": {
              "type": "Buffer",
              "data": "HYrARZp7bYfl75SJx1U+lYiNgF2Jg6kAbnEK3QnDlvY="
            }
          },
          "An07MpqK7TDbauznb3w1fLJkWGcPombXBpAL+rdjEno=": {
            "valueMac": {
              "type": "Buffer",
              "data": "wZAj6AE5kRjKB4DWI+ZT5oQpA1svnGSser4vuohzcTo="
            }
          },
          "ytpbyENAjKLp5WvKbMR125xU1sY/c3LpXr5Gi3kjAcY=": {
            "valueMac": {
              "type": "Buffer",
              "data": "tWlRNWQQ5nbD8DySg6mJcVyb1UZD543Uo1+tbcZQzlw="
            }
          },
          "EfN2mAMmh4cGSvZr0vtUpUJFNo+QWmbQApw0xs/h6Go=": {
            "valueMac": {
              "type": "Buffer",
              "data": "r7XQEVgaUiv2t2k0GlvaPkK4zQ6gjJ/wcYTfbgRkpk4="
            }
          },
          "6XcRonMFYf/0wMmToShfzukb1fMcuDvznIeqHdXDkmo=": {
            "valueMac": {
              "type": "Buffer",
              "data": "L5P1pe6cC36I4XldLE+3N7moKiOeo0jzmluqheQTLbc="
            }
          },
          "JWYiVzSHooXF0sFh++Ty5pSRZoRk+hLTK8Vo4CSEh2k=": {
            "valueMac": {
              "type": "Buffer",
              "data": "dlPaMgwMO7Hr8zEsEm/OiAFGSgR31N+6B0dB3x0+l2k="
            }
          },
          "47Lh22NlsdEXA+bEqwq7M+ewL4hs4S7XMdHU/eGX7zE=": {
            "valueMac": {
              "type": "Buffer",
              "data": "N/liFzdOMKhml8s40CbxGonzAof/Qo1PnOw9u42pNLg="
            }
          },
          "fDG3d+XR6JCdgAlcJv7BQ2087lX1Fal0vo5mK09G9BI=": {
            "valueMac": {
              "type": "Buffer",
              "data": "RuQ+RZ/IIrnz4efz3PpC9jtPNmyAfMIU58zY5w7YPbc="
            }
          },
          "s0hdx0z1QAArfGedXOzQuEI6g5DmT3BVnaNSn4pUfMM=": {
            "valueMac": {
              "type": "Buffer",
              "data": "1CJ+UL66yOqxwyQ2byyaCp8SMuoPxQm4c49xtA9/DZ8="
            }
          },
          "VOINy+1PgtH3Hct5Ba8wORDAAkDel+Aym8I/nQTRQeo=": {
            "valueMac": {
              "type": "Buffer",
              "data": "5Zrb7jq9M0NFsTfoxpaUBcl7C1uCo4aas7maIjEEozc="
            }
          },
          "8wDVa+s2UXzhquGe5PgrXpsPFhWnR3DgHZMpJ7l+SUQ=": {
            "valueMac": {
              "type": "Buffer",
              "data": "PZkKul3wq0tK7iP7Y3Jh4ZuzS2SrO2ZOhUEFh6EyCpk="
            }
          },
          "auvIgB1pGJKxeXI2L2vgvzqguVPpQ0xUI28JssBJTPU=": {
            "valueMac": {
              "type": "Buffer",
              "data": "fT5XhC0xdcl1C+fs7Jl9jbhq5tqZdx4JgNhV+J3c79c="
            }
          },
          "jLcR1Hx7Ckg7xL475i7OqI6BdcXhtuswKVyRJymsExs=": {
            "valueMac": {
              "type": "Buffer",
              "data": "8+5pz06/cE9UHcbxz9tQzhxZcIpNvYZpPAC/R1rV1vI="
            }
          },
          "YNvcxc/AAA8kPjEa3pa+rGrAnZNJ2qSEIx+U9XcIcIk=": {
            "valueMac": {
              "type": "Buffer",
              "data": "48ZqbTnuyzH6V7+X5Oausj7pup9TdElME/+5xX0npuw="
            }
          },
          "BNlUQfVX0eSXHgDoGbn6uBzgojmQPLPIgC55LWRIytY=": {
            "valueMac": {
              "type": "Buffer",
              "data": "xgZABh7jG6iHeXh8Yog3bkgWNXYiq1G/ClBTXOS7sp0="
            }
          },
          "MHiRSiSCFsbYHA9WjDpfV2AJkq8mx37dgI6yoTB3I+U=": {
            "valueMac": {
              "type": "Buffer",
              "data": "0z5JJ7qhscUhFP6upx19XKuJDZGHA+8jrFqdDgMs+3k="
            }
          },
          "/bXgcHVqD08yW28OBeBoInQ4e9Hghenajd/ghZdCVQA=": {
            "valueMac": {
              "type": "Buffer",
              "data": "BatBr896Fe7yG6de5Xu7Wgcoz51Lz74FBZaqmGEQb8g="
            }
          },
          "Lfar1jpRGf/T8HFi+EX2xhaOqEU6KR7t6mXbOpsSwy0=": {
            "valueMac": {
              "type": "Buffer",
              "data": "jjl4gb87KjojG2+adRmYvIW7QsNkj9oulvP/8z9aUx0="
            }
          },
          "NCQmfEo3kVv6UQG8NjnK5XsKzN1LiUmHGHAZvoT3v0E=": {
            "valueMac": {
              "type": "Buffer",
              "data": "rHQDYpU9ff54L6s4xpNhRvbzMiwaNiZIoUM4Ma/gsEs="
            }
          },
          "xFGnpCA5atCLfzgzL6vr5qeG2ntjXqkGiMbX0HPAY2c=": {
            "valueMac": {
              "type": "Buffer",
              "data": "lEOY3j7++u/v8yMGtUChttUkUwRKZ/5H/iy577qyBGo="
            }
          },
          "QwfgQ3qEvpA+2QVDaAzStc2Q+JWGWwvDHYCdlewYZlU=": {
            "valueMac": {
              "type": "Buffer",
              "data": "u+KATsDHitmOzPoAhl9Jp25r5bFqgIag+JldjrBPcZA="
            }
          },
          "L9G0pykDAn6xyiMeQ8IieXK6zFEYj2qfNh7yuXWFewQ=": {
            "valueMac": {
              "type": "Buffer",
              "data": "gdz+4pR52tGLsB1QYXkk0GNyspv0n8JotTJCCongFio="
            }
          },
          "u6l9Trlppnkn22RrWUIE2wawfJ8adpjCZd77RMdOa84=": {
            "valueMac": {
              "type": "Buffer",
              "data": "PE/GiLhaV2k2APyeebF6ETW1Obr7jUmDbLfRJ5yarXA="
            }
          },
          "ClXk2Rtox4UwbTlNCW5jhrU3z3u5hJg9mn2/loGD9p0=": {
            "valueMac": {
              "type": "Buffer",
              "data": "VLGBcGsIXT6r0o+opVecsAiL5EEL+LtxLKeWYWoY3eY="
            }
          },
          "ZwddtGJfIxtBrlyYSvV/SQHc1DbrslyXem2Vk1STbk0=": {
            "valueMac": {
              "type": "Buffer",
              "data": "GZlxWCLu8TZeqAurkQ8Ii7QYvy3Xo1mQ3Y37SAMBQQ4="
            }
          },
          "TqxjOxbKvTPTsgOl4L7kAl9tCaskiWGBj9JY5eONlL0=": {
            "valueMac": {
              "type": "Buffer",
              "data": "u0tPy5AdNg534j1h1sgp5pGujP2mmloSW4y7cjUJIho="
            }
          },
          "5R4a8P/Q+TwrlMshxFb8KX4T7VB3Jnng/gHniJn+ueA=": {
            "valueMac": {
              "type": "Buffer",
              "data": "5oNktwcMajhdcZmfshRsL/nx2k2+Js0KT4/1rG+JbZM="
            }
          },
          "7rerGBRIdJFIJgHysfdbQj6QFAcqi1HJBhlRKPY094c=": {
            "valueMac": {
              "type": "Buffer",
              "data": "JfZH0LMn8TW9FMQm1WCaguLIoGORzU8s+yEIIxAHG+A="
            }
          },
          "hjV75EhV3LdXzas9mzM9b0WI3qK+LYZtD3pIt+8Q/Aw=": {
            "valueMac": {
              "type": "Buffer",
              "data": "vPOnGfu/RHM9JfaqIIMzZ8dPGF7UwQjNX5RfTPv9vbs="
            }
          },
          "87mGoo6Ll6BReyJVVNIO4gHnrI/XyDSs/7JinEsGFXQ=": {
            "valueMac": {
              "type": "Buffer",
              "data": "vbi0L+lF0Ch3St2q2URKbabePhf2FMLVmdyr0PBWYOw="
            }
          },
          "bfu1HdDBTjKsfq04QX7rYwzOOwOHMl/4jvj6Hxwv9+Q=": {
            "valueMac": {
              "type": "Buffer",
              "data": "d4lA067AfKHhJgGs2fbOTTb1F4/Wn8/OPnZmeLFHyhU="
            }
          },
          "f3vBIFZ63gr81c935txaj/UMEqGHb6SWf0gJQsBvoq0=": {
            "valueMac": {
              "type": "Buffer",
              "data": "XEcf0RHRYZpc7HS6F2u1/MaK1c7qyaCd9TES0gQq7Hw="
            }
          },
          "mhyRQccUDtJ9lokc1wlHpCq3lbygic4gdMQ/y/E6uog=": {
            "valueMac": {
              "type": "Buffer",
              "data": "lxqPeoCiCruSavQ+Camtaeob2zhRCiyxBOR5J5voFU0="
            }
          },
          "fNnm9tJnWauBJrM718pfytjNHP7yvv+TtvZasOsX0GY=": {
            "valueMac": {
              "type": "Buffer",
              "data": "J6aJWEPrl+IpJs0c25xtKyz3rxcugDl8N0pQuhrDdsc="
            }
          },
          "1DDdcV0iq9vjUXO9q1PGCRcIRsEGCWrp0is4mc8A810=": {
            "valueMac": {
              "type": "Buffer",
              "data": "jfDm+i4at9bpQmlRmM7/DPBMCSm96/iUcESww2A1Rcg="
            }
          },
          "2b9/3hkGrUvTzKo6KuW+oP8D0pAjQTDmtmyPy/MPtbU=": {
            "valueMac": {
              "type": "Buffer",
              "data": "HwVBAT+iv+cHbAXLYEcf+VrHsrgD5+l0QlDIqXG1IhY="
            }
          },
          "VFCtfQX/8jmRjy8hbABRFZqyzLSEL8xtjkKYcxyItHI=": {
            "valueMac": {
              "type": "Buffer",
              "data": "htAwoqjH1fvZLmGqLqNCY24AZa7aXpGbH7zU/JBQPxs="
            }
          },
          "JIP5wN1lfrgsNPoTkbQbiDfYbB01uT0FeVKN/SmB5k0=": {
            "valueMac": {
              "type": "Buffer",
              "data": "ij+KYQAGVU0ZnUabj/mXvUqGiuklBk0Mol6zcXcR9PM="
            }
          },
          "nnuI1SWl+TfJI22O06h26BBbENdznZ0XY0gZI2E4zns=": {
            "valueMac": {
              "type": "Buffer",
              "data": "mzMdifwVxg0DMt7l1e03eS8zu/HbEcnb3OhTnBgt1Wg="
            }
          },
          "vb4Zs/58hsN9qQJQB/sYxCdIbeRB0hhsjEyDV1XPvFw=": {
            "valueMac": {
              "type": "Buffer",
              "data": "bWsCL9VeZEiZP/VmJ6Aioi+VTfB0t/itqNOAkDIe6lk="
            }
          },
          "2GbhaLVYdkO3BljgnAu6gobzZJ7LZMLq51VYlx9QJkI=": {
            "valueMac": {
              "type": "Buffer",
              "data": "3fTqw7DpDMr0ZAwtyfKaNskW6vSNXxYf2UdzdGW+hJs="
            }
          },
          "mtofj/ZVetU7+m7mhhDVVf/g355duJZHTG/sYj8SuaM=": {
            "valueMac": {
              "type": "Buffer",
              "data": "6qt8gHcbrJ90qoc4hV5j7gAqvhuJDdOPsaLXgYlpg5k="
            }
          },
          "OCGF7EILe/Bl0RHR2yz6+2Ups1z3yYZw9Q1NJ7D0cv4=": {
            "valueMac": {
              "type": "Buffer",
              "data": "nTSNxv0wgiu3YB33oKgZG9fJsZN3RVJQDNFUoXgEhfo="
            }
          },
          "0IyFaiQvBh9DUf2WpdbEUWEn4J44m2r805ZTYIc39l0=": {
            "valueMac": {
              "type": "Buffer",
              "data": "iTerxw0kcEpJfo6kNfQ1lgVg/VDG7yVWskeMVFKMYiE="
            }
          },
          "v+N/MvGazXzktr6f2Os+yzQF/j2iB8Tb5jkHS/hWmWQ=": {
            "valueMac": {
              "type": "Buffer",
              "data": "HBuN5iSk7JcwlI7LfMyfvddYvEdIUxSum0LziSDonVU="
            }
          },
          "kmoDFxpynb7ozDv1vMmigxMPuMlwj0AYLbYk5mxLris=": {
            "valueMac": {
              "type": "Buffer",
              "data": "p/n6QPCvNNKiFohXWOiNBz3qhGN2ZGbat0iIdQm7l/E="
            }
          },
          "nFqIQo/DyEngOIDxqJq0imMEOUe/DC1n+KgeZEVOPf0=": {
            "valueMac": {
              "type": "Buffer",
              "data": "oIYSJ+tDjOvLpLefq+YM4iDiFw2StbWYitDmZgj0wSk="
            }
          },
          "C0JuOoWKDZbIwSKJ4SA9NyKiZ6UWh3KEGETDdERqvuI=": {
            "valueMac": {
              "type": "Buffer",
              "data": "qeFILreDQiJAzWslH38D62z0TaQc7Jo/T/pPoVFgfss="
            }
          },
          "F9rTHNBA7J/sXb0SswnlqBITwPHH28d7d1i6FGBqbrM=": {
            "valueMac": {
              "type": "Buffer",
              "data": "bjmhedp0Jg8ormIKQQRdFm+h+9jkxilzqkFGlpRTDgc="
            }
          },
          "2gKLOr8D0rlwUQlZNkUlHSLMZ975G0maNY5hB47gruE=": {
            "valueMac": {
              "type": "Buffer",
              "data": "TXPC3sL6cuEwfs27v376EZ2khP78loncoqCj3DPK+TQ="
            }
          },
          "HGmfjGdnNYr+CCSECH7x9N+1hIYvtuCtBjQyt+Spppo=": {
            "valueMac": {
              "type": "Buffer",
              "data": "s/FKWxYq4i0UmKW+viqIRUh89cCPD3TfUdiI3biIfgc="
            }
          },
          "HnfhP/KapOlVW517Rm1Jzi4IPzMXtetUFjZ9cF3FbNg=": {
            "valueMac": {
              "type": "Buffer",
              "data": "wl914vIcHW3x6eW1IHR94saYQ0HaWlxl2C6Y+9cumQM="
            }
          },
          "NSHIV5oP6yO8TypLc4eeZGI/khvUvS+ZRqg8wmcmd/s=": {
            "valueMac": {
              "type": "Buffer",
              "data": "d5/o+8tfFUD+8JIA0tyTBmnZ8goPtRg4SnYDFbExZI4="
            }
          },
          "+/OVFsxsJ5rE6id177X8iVQZQvCPLRzJ621X8g7DjSk=": {
            "valueMac": {
              "type": "Buffer",
              "data": "2vNtXOpGc9XXp2lt9wPkynljUI11egyMAWBKydOJz1g="
            }
          },
          "ISYaJDrNN45KQglpL4Uwly2lqNPja+oi75/ea1W8lbw=": {
            "valueMac": {
              "type": "Buffer",
              "data": "drC+gYYjUWTPANuy/YZRBZzgJ2/9G0VaVOPtj3Q5ee4="
            }
          },
          "I2uckhYOng263YNBHpp2xkut41ZYpl72CUFE0AioGSk=": {
            "valueMac": {
              "type": "Buffer",
              "data": "eRK5tipcdwfx6XTvBWDffyX0WmThbiHiSORpd/TREFM="
            }
          },
          "NrVYS9OfvSzQ8TvM2WGDJAvOHfT219f4W+skrHMMbmU=": {
            "valueMac": {
              "type": "Buffer",
              "data": "oZaOxBwDOD06B7hRYOhHR2jyYHMNFT4fURV36QcOa5o="
            }
          },
          "RVFzdLvVbOEJFNTv/OTDSQkDPMLSnmiIxX3MKdtDlRU=": {
            "valueMac": {
              "type": "Buffer",
              "data": "Qqapuh+e8HOE6Fn84OuvuvGqJnkW2lQwnuuZHx6Jnzo="
            }
          },
          "/WsWvkoAihh1oYVzLfXmFrkKfeAZyoLHZTdVBchAq7U=": {
            "valueMac": {
              "type": "Buffer",
              "data": "V2F6lGQ1X0kntOmERa5/PXWVdYqo6buLThcyTlCMLCE="
            }
          },
          "oD+0G2CmvDqhb+9rUhunOaTMBQfY9Vy96yZLNtxK2yA=": {
            "valueMac": {
              "type": "Buffer",
              "data": "88X29mUgfTJ7gWR4bb/3hky7wbJ7uLWElXnrU8WA3Qc="
            }
          },
          "L+G0ZBvDlzXl4uFKp8TOFbU5l+3Ekj5NevuIDx6eytw=": {
            "valueMac": {
              "type": "Buffer",
              "data": "nEy7n4JJL9o9CH48u1pkFcn/gcmXQC4D31aLWOc4neM="
            }
          },
          "1Jl+sn4RTTZcadhRO2fJsnvlQZFlOADQ555PngJV928=": {
            "valueMac": {
              "type": "Buffer",
              "data": "hUuAdV3m5FWNUq7s+o5G9iaCohT3NAOv6LISzdgrnFo="
            }
          },
          "NRo9+i3fkeOyAQPqL91XAQ13iAbqgpEYxziPir4F7Iw=": {
            "valueMac": {
              "type": "Buffer",
              "data": "dM8DzBK+roaw2UFAdmJmdhXXWN3a+jl4nJT40h7yYXY="
            }
          },
          "GpkUHltLVFFjkK60rWc5BfI1e2ADVLncQkCGXTk5JjU=": {
            "valueMac": {
              "type": "Buffer",
              "data": "iI3D9YNlBCS8/Zowft7q/bPXqUUcP2qnRHDT2gHtYjg="
            }
          },
          "h3c2Qbj5t/ChTsa3YcXkQGnDaBpymFUL8rl23x0YH2c=": {
            "valueMac": {
              "type": "Buffer",
              "data": "b1LzN4kxQfygqcT/Tej+/y3yqHcMYFf5YgZAcpcPt24="
            }
          },
          "MUaFM/IX9x3mKTpfhjVTdLePlOHDF8eoYSef0X3tJAY=": {
            "valueMac": {
              "type": "Buffer",
              "data": "QPTn7tG1FZazyihSdExxFE+blSeqvhSdsV0PexA0Z6k="
            }
          },
          "/AgRH68DGjPThTnz9Qqk8BRi2cq5qKHyzIwwDy2osm8=": {
            "valueMac": {
              "type": "Buffer",
              "data": "RXZWA7ZxWueJUdTHQt510cTOLMJGxOeqvgZZPwiOA40="
            }
          },
          "UrGn52CcRwuTKd7rYHuwQwzo1uK1FB7W20FLv/ElgL0=": {
            "valueMac": {
              "type": "Buffer",
              "data": "dHp+pfEwoPVppRneWPr/gbtPQahPvbXLIaVmNAj/J6A="
            }
          },
          "IBb0OY2JMlSL7UkmHo/J+/q7EEYrwKHjSkX30lJPh/U=": {
            "valueMac": {
              "type": "Buffer",
              "data": "w/4AyrA2uZIek/+EzAsq51aIvEoboFsYsB+vtrj2Uwc="
            }
          },
          "pX7uySysINu6p49HI5iKSW9dHmhq3srgyRQlVLvBTUQ=": {
            "valueMac": {
              "type": "Buffer",
              "data": "XsdCbwVQPeM/ArL5TV4NwgAnAnFexEKqXdA2rhss5eg="
            }
          },
          "GwE0Wb4jdaQ/Kglb9faz5WR4CcDkccq1HXckeNWpOC0=": {
            "valueMac": {
              "type": "Buffer",
              "data": "SWksJHGIPPlRx61eesr5Vo9ZkrObhJupYCWysWokOxc="
            }
          },
          "a5QZBghT7oT8b//PMFqo5jkb6MtsCCzYgnOjiIw2Sno=": {
            "valueMac": {
              "type": "Buffer",
              "data": "+VJfXp4FTENdoOINQzx9t/k2HZySYLY+agTOZJ/MZuU="
            }
          },
          "rm3zTsDqXkR9G5LpVvtQNvXlBx83tIOZLWKCEzxoI/w=": {
            "valueMac": {
              "type": "Buffer",
              "data": "kKYcWx9QD7Pim09kljE98UzhIQsmsOAN8V0kYO6U3vk="
            }
          },
          "vBw1691RSlvYtl5yJ9lX+hU7WytnVoMTFL3YZFq7rFQ=": {
            "valueMac": {
              "type": "Buffer",
              "data": "rodkRKCEdbiftNmKk01GL98k4hMklxKaBD8uifUb95c="
            }
          },
          "8PealsYXZqOyYegC/pzYHs1QhAu/LhKj3T6tUsxvEwo=": {
            "valueMac": {
              "type": "Buffer",
              "data": "AKsyxh6K4GIL7DlzDMd210kqpxB0qV6KuALX2lhnqeo="
            }
          },
          "OJ0K/QsO+U6CyuZq0Ewas/QwbovOXeAQprWcVwmrnho=": {
            "valueMac": {
              "type": "Buffer",
              "data": "yp5+58oJ6/PVClsOl3Kktg1PeVu3NAnqmiU/3zBauco="
            }
          },
          "eNf00RmdnzsFtMU2iDmguOGEX/Keam3ljH+GxvOrxO0=": {
            "valueMac": {
              "type": "Buffer",
              "data": "Jd0YUvcWq0OAVYdW1LDdROSvNbTXWZmdF5Rx9RUB9Gk="
            }
          },
          "ednYzYCK86mS+j8ydC2dCoWA3MUSLtZwRvsf5uLBoFs=": {
            "valueMac": {
              "type": "Buffer",
              "data": "Y2AJFuvC6QpN18mR0gxm/3OrOAnUIKPn7oTluvWdjl0="
            }
          },
          "C6I9eRRxWtBDl5RFupISJmLe4m4/ySS3DaDUpRPxW2Q=": {
            "valueMac": {
              "type": "Buffer",
              "data": "IummWi/eSMU6mDBhn2yDP7nwGZUn0cJQHaIjQ3lrV0U="
            }
          },
          "XwfCTs2d2kgI3HTqoDWCC302Yb5//HZHbB45qGelJ6U=": {
            "valueMac": {
              "type": "Buffer",
              "data": "ZgnzYUXqQ+TLiwfSS2qpF8cOHGXBDvco9ohoEwoCEC8="
            }
          },
          "wwHMkhq2Y07KvU6lPP3s/Xbm8hxX607ayhnpyvbliI4=": {
            "valueMac": {
              "type": "Buffer",
              "data": "hMlD0HLh8EYJoPVH5HE3Bi+oht68zBsJp6xXNnK8doM="
            }
          },
          "COohKD3bongBqDFv9+NMr8TxnzleCdbD8mLl5LJr60s=": {
            "valueMac": {
              "type": "Buffer",
              "data": "UZLcEv4esIMp1EO/OA02AHmEBXmG+QfDZCGDfprMwPM="
            }
          },
          "WJxXFH94TcQHivx94AoPJ8IFP5eR7ZeFBjQ93TYACY0=": {
            "valueMac": {
              "type": "Buffer",
              "data": "5yoDF5W4GjPY2dIcf4GtnhMKYGO7T/aRF8jBUNJBWwQ="
            }
          },
          "5A7cFm99zoohyVYekf45HNxnjAwLYXefCZvwZNDYJNA=": {
            "valueMac": {
              "type": "Buffer",
              "data": "DI9oh8VR2MI+oeNK+nSlquLYEXUxISVrLO9p3LU1V44="
            }
          },
          "kWZ5LyPvoPWJrM05BiImaBdnOSyKtL9E4c6ghkrtGEE=": {
            "valueMac": {
              "type": "Buffer",
              "data": "9rL1l3v/TIOjUtgMecCDv6whkr9zQzCwbhx7spFR9f4="
            }
          },
          "8G/hcUwgwP8f4hscoLyC0XhYRhwsBDw2F8zuzOgKEI8=": {
            "valueMac": {
              "type": "Buffer",
              "data": "IlEeR79QbkyRfjSqvTxeq+wevDZqou6qde2uj+AH7y8="
            }
          },
          "Bk0FBfE8W7ndc6x+6uH/VqbtTIZBTAJadh6a0v8FfjE=": {
            "valueMac": {
              "type": "Buffer",
              "data": "WGhaV83YskEedlxdaAyR0wjymqjEy7bEP5+HbzW4+zM="
            }
          },
          "t6GWU6ohsybVxeGSKMnzQ8EV/E8laiy8AqbRiB2GLZk=": {
            "valueMac": {
              "type": "Buffer",
              "data": "8LV4VOMSZwDxQ3OmLrCogVQxOwDydq+AFTjexzbRf1g="
            }
          },
          "3YHMYeIrcBgPMHkXu24uTzdhpxihjDxKXZlfkX6XieM=": {
            "valueMac": {
              "type": "Buffer",
              "data": "chnT2uaVEBL4kTSeG+kaf92Z73hWSEPWfhK8H0tj9qo="
            }
          },
          "/f3Q2QniyrxHhiljbifQNXb3lkGzyboTXhMmQUUhnag=": {
            "valueMac": {
              "type": "Buffer",
              "data": "9YVIUt7zQszIzw+WZI6INKMtF3inhQIVXwFW+31+1DE="
            }
          },
          "/5G8LWfUm2yuNFKK/DlWfrw38YMQm2ueMzZ7yfg7DLI=": {
            "valueMac": {
              "type": "Buffer",
              "data": "lVheAuk6X2vTq7DcrN8tD0mqXH5gBbpTNwe8b7e6huE="
            }
          },
          "CyBzv6wh3q1lT5sfap0ynTcP4ZLjb6fs1glhjCDhV6I=": {
            "valueMac": {
              "type": "Buffer",
              "data": "3ZRgeKHxt4au7ki9zPHccgFjYw10xqodM8dMjxSaGtA="
            }
          },
          "H+oq2/OKItf+dmGMokICgs3ajUg0BtSef0RM5WaAPHs=": {
            "valueMac": {
              "type": "Buffer",
              "data": "XPrdktftk6sj1ZXFk3Mn6M+58GanYvu1Xjx64kRsw3g="
            }
          },
          "tPjHg1JqS1tiOm3+MSY6UkocyW+EeF931KAFE4/yMjg=": {
            "valueMac": {
              "type": "Buffer",
              "data": "db70r1u5K6U7pU63TE62+RQYzRq5GbGNjC8rcgTMLJg="
            }
          },
          "zZhBgqXi+Z0OhLb1Z4HL4yArt1SLTk7nLlSo8VscpsM=": {
            "valueMac": {
              "type": "Buffer",
              "data": "xVv7CoJHAeZQzsoZbemWnQwTyK8Am6TDPJQYub5vCwU="
            }
          },
          "QVpelb5jJwZ2bRJUYL5pvYhR2HxZkZV8jlH5MhYu7jk=": {
            "valueMac": {
              "type": "Buffer",
              "data": "/WRppysU1p+HbcxIgBQwfM6M6XZLnz1JSGxzTe82XKo="
            }
          },
          "K/wV8N00QgECt/oiTLzo7e0hi13+UeKv9rmLSESgC3I=": {
            "valueMac": {
              "type": "Buffer",
              "data": "nJFrSYqL8NfS8wRYOwwugMsv9ROAsdcOHj4Mdbm9jbQ="
            }
          },
          "oiQYAuWtDyVIs2+cY/TEUrJBiEsk8JtAmMBLCsUh178=": {
            "valueMac": {
              "type": "Buffer",
              "data": "sQ35pqtMUYyFEVacts1R6eb6ZcgfZ9/XwpS9F5eVZCU="
            }
          },
          "oDgLSjs9oIBpRSR7JI28TZ9ZpAnYr7hOeUfZyZ40U3I=": {
            "valueMac": {
              "type": "Buffer",
              "data": "J2W7qL6wparnaWA5u/wIavAJTcXH2AMHOF5EY+9HTGM="
            }
          },
          "tE9XWR+PwExmkK15C441zLXriOday94qZ/dba/Z/SO4=": {
            "valueMac": {
              "type": "Buffer",
              "data": "7Sv6tr8n1B6jiVWtlKI4XbdmrCVO5sxhsLtfKUvdbfE="
            }
          },
          "6ep2VBbseX23Et4mT2rKb5dUFFXQwFM/Az13+oRdfpw=": {
            "valueMac": {
              "type": "Buffer",
              "data": "GptzMitXyt9iXb3fQApyUJp7ay7s3giCyxgOROzIUDk="
            }
          },
          "kKDdbBHFyUhDe5GCKpW8LWNlHPdU8sYkZ8js2DWTzjg=": {
            "valueMac": {
              "type": "Buffer",
              "data": "esUWS9nt/2LlaO0H0xMIk7phTfbXxZdrgeanowpey4U="
            }
          },
          "S/xThn0wAJ6MOleR7avGZ9RPPxAb3OdYopk6h+Fnhr4=": {
            "valueMac": {
              "type": "Buffer",
              "data": "x8kFfSAYIm0hA7UeKZurrb4kgDiJqoVEzeBHJ8/tngw="
            }
          },
          "MI/lVLzr1aOQ4HQBnKTZ7FG8fPdihbdR5HPneNSEPHE=": {
            "valueMac": {
              "type": "Buffer",
              "data": "3O73ZmP+QMcB0f0ejEgXGlJTSEdXp0qOAPPAHvgJV9Q="
            }
          },
          "FkzHwbsk6QvcBw3gsu9eRddMgtMNTHj5fd9NEN2bRxE=": {
            "valueMac": {
              "type": "Buffer",
              "data": "QXpjoJ4FY0EMwMDqmDYlV0bRzXdrYhiUkinf9epOjpo="
            }
          },
          "X0/tK5qxx/3UETWAz8KmZNSycy+XBRCYWVCZg57RMrI=": {
            "valueMac": {
              "type": "Buffer",
              "data": "uK3EhnhvgqY3kmK8j9qsogJExVQ2Atp/vofI7wfW/h4="
            }
          },
          "jeG9syt/8bfL4iAMka9J28tBUbzJbRShSFkttrZBjPA=": {
            "valueMac": {
              "type": "Buffer",
              "data": "RoL0fZN8TgZsO17Ss1Z7pSBhySRORwnfnKDWKMq0PZc="
            }
          },
          "aG45QEgKSuDzHqjAlS62sL3iDgPOqKpPENw/HWFbzDs=": {
            "valueMac": {
              "type": "Buffer",
              "data": "7n3gSMYevqp7s0StY9BNi/YQQ7qA6iF75OZl9984Wt4="
            }
          },
          "U6TkDHrEqeNVb5yj5BagDSSlU6FWWUlV1pvprfYSF7g=": {
            "valueMac": {
              "type": "Buffer",
              "data": "Qap03Oyc+3niF+VKKdmArDA76ray522GVj/OxwuWPIs="
            }
          },
          "yCiaF+jyE3TxZt/9O5FAwVrNNeey1rarnojdEXqv2PU=": {
            "valueMac": {
              "type": "Buffer",
              "data": "3ePhO1F5inrnJD8CRv6jQrq4uQjLMEce1zgjC0GHkkQ="
            }
          },
          "Efw79XulAMttmJsEaSTaPjdaFztqrfdqxlDNUkM+qZs=": {
            "valueMac": {
              "type": "Buffer",
              "data": "DeOFQxNveJX3S9UpJ1mCRL3P011g9aF/1y6+2Nd4TAI="
            }
          },
          "JfPgypc8mvdWA/o17lfefDwlTVnuwZegiaDo4Zw02dw=": {
            "valueMac": {
              "type": "Buffer",
              "data": "RbSV3KisJHQ5SMJGSm44FFI4bSM3PwuTBjBS6fDOdDE="
            }
          },
          "POdbG9lwGLhGxLTRE5FgFv84pvJhra/y00tjyvRAyA4=": {
            "valueMac": {
              "type": "Buffer",
              "data": "AtvwqJ5p1afFdl8/JvPRTNcc6J9gPDnrozBpp5Y/e3E="
            }
          },
          "1rC9RvV+lzwXSAiXWjIMdIc1ZXtReAmBKAnZthzmjr0=": {
            "valueMac": {
              "type": "Buffer",
              "data": "jmOr/pVnoOY5qur5b6cAV6473qyKi14xJMjnqnGWGkE="
            }
          },
          "l4jtfzFKkBcxFcSUbMY8Reb9meKtQV1GRX0+5bAbLek=": {
            "valueMac": {
              "type": "Buffer",
              "data": "rPKzqMTb78gRmlt/oorYE1kCTKB5m8+zUaIj3qbvt1Q="
            }
          },
          "yQD/jBtyt6nsHDxdVbTO8uONO8CdFKG+RazUmTmHJdg=": {
            "valueMac": {
              "type": "Buffer",
              "data": "Z/UgqY++kwNYgt2IPIYayoDu1U2TFAL0hKpMAzCrBsA="
            }
          },
          "B3hSJQNngVRAwWrwLO1+88djcahcYka/O8Fo14gjQ5E=": {
            "valueMac": {
              "type": "Buffer",
              "data": "+qmbFsvRJAgNo2MyA/vrzNTUwi+OAjUsMmxfIXO86SM="
            }
          },
          "R5T2xZV3XHevM7sd/4czm0hFBbfnsoHOxnWjNu3xoyQ=": {
            "valueMac": {
              "type": "Buffer",
              "data": "lH6NHEFoCdsulx203Kglu/ES9Ms9LLfF5mphKI2hWho="
            }
          },
          "s9tibNVaaYai1oA8hSmx7eh+tVzopqiDyvL8BWVlGxY=": {
            "valueMac": {
              "type": "Buffer",
              "data": "PLksz1Qc7Q766oazfaOGOO6JKl/VMtPnRjkIeSIaAGs="
            }
          },
          "CeaMl4EQgLClxs/RkMD1BZ06vlClhTZkVjXBVyoB91k=": {
            "valueMac": {
              "type": "Buffer",
              "data": "YM3v0J2+KwzjLwSWd6cUMt9Z+VHPNDeocPk+sIyzFZ0="
            }
          },
          "0slXPxYb7ZYlRrBRzkpsyjqwM7QSFF8gGJGYniWxmrg=": {
            "valueMac": {
              "type": "Buffer",
              "data": "f1iflnZmwckYDRBCDDLFH5nJlpsHnD7odNV2xQ8rTc4="
            }
          },
          "+h0otdWWjjqxYAr091HkZfGPck+tjIa9jjjWiri1pcA=": {
            "valueMac": {
              "type": "Buffer",
              "data": "CyZvGZeV/jWJSCmtIikkkMfskU341dGHI5OXK/8LFDA="
            }
          },
          "NCwThn2KJxKCV6h+zOC9n3lqeZmO87V9oM0RiAQRNvc=": {
            "valueMac": {
              "type": "Buffer",
              "data": "n2W7Wvg5korwvdrgsgFoNWJeCr32sCy2Co3f28hoh2U="
            }
          },
          "HxQ5uyjVprixD4Yb80U9aUhVMUvnDyiQ5PPbLU8AUmQ=": {
            "valueMac": {
              "type": "Buffer",
              "data": "EPQeJUuHoLFN4zkvZdTISZTuSTw+eKvjqbElxn/RVR4="
            }
          },
          "LkxDhJf0GWN+Eot2g0ZOOIknG+yhT5xliRgsRFPTJMw=": {
            "valueMac": {
              "type": "Buffer",
              "data": "m+uEeqXXcUTMv3OtQblqJRmlgVWvHIca4o3/5FW5hNg="
            }
          },
          "Xxa1nsgMl4OgrXi8lCXWGpkCSBjHdsQKbvyWvBljiPw=": {
            "valueMac": {
              "type": "Buffer",
              "data": "Ca/PM/o6qCVaco13yAN6XZgAyzzaCWtlnpdb4V2/sI4="
            }
          },
          "mhPY6pE29pXcYe/0lantYSB7ffgoibAzHAEEWA1mgiI=": {
            "valueMac": {
              "type": "Buffer",
              "data": "VCHeyDg95YZiJxeYrH217J3z5UaD+HK/q5a17Yln2lA="
            }
          },
          "A64jC+GmCg6/W3i/L7h4cpxLtLdboETWVLECGZGLpEg=": {
            "valueMac": {
              "type": "Buffer",
              "data": "j7CECpzN1WcNcqp01IHttmQoQIp6E2pqrcc46Xakfrk="
            }
          },
          "45lbIKnt16t4vwuj1T3sp9uniylNXzK3rLbk3Jvgn/8=": {
            "valueMac": {
              "type": "Buffer",
              "data": "ZkmBwxHHUvQh3MviG8WYvOVRCtg7cOMzZlnMeDUnqZg="
            }
          },
          "TFlj0bPcUC4ejC38wnL8kJDJ9Nt1wDQ9fZLgghHwee0=": {
            "valueMac": {
              "type": "Buffer",
              "data": "pzZbdykq214ZC0ZMaApKAyiha0ar1pTIh47RyHCbSn4="
            }
          },
          "hRNfjQKfLntxAQAE/IHBmJ7i8KJLMbRuwFaXeR4F94M=": {
            "valueMac": {
              "type": "Buffer",
              "data": "nFtskJMX3d0CVklQToQ5rwbT9/+IpSE2UQMb3USecSM="
            }
          },
          "nl2sPfG0w9gRaZehLZ1MEn6MHMwMwJTqhs/C/UlauvE=": {
            "valueMac": {
              "type": "Buffer",
              "data": "yQw3IXGdEzAw4xZ0AywN1Nbff/WsSutuwbPPjRVHTK8="
            }
          },
          "VcR1sxwqnrKkSqyph/JDNrGXJEwppdvlNR8P5PychoU=": {
            "valueMac": {
              "type": "Buffer",
              "data": "+Y3e6mavbxJsCwGdgxkLbDIMpgKYZgTfBFox/EIquZc="
            }
          },
          "wEtSAi6789sbtsSr5SNuPXS/FocsYnErFq69VrauO58=": {
            "valueMac": {
              "type": "Buffer",
              "data": "joYDMRIpsQgQvXzxAu21eEJHE7zeeK8b+9TFtbRNxgY="
            }
          },
          "4KVMbU2defCR56fc7GQwkg/a0C7fbOq2UrMwHXX86L4=": {
            "valueMac": {
              "type": "Buffer",
              "data": "jkXX4zA6pov9Q+5Qv4IGWDqCgsv3NdhnyTSqjw6SWTA="
            }
          },
          "x6bDh1mDF46oRgVv4NQE+dBFtdAy2K7AV/lODaQJf64=": {
            "valueMac": {
              "type": "Buffer",
              "data": "LfEF5F40Av4h73X9jL3MSfgKqTsH+AIqa7jNvVHB7zU="
            }
          },
          "GYbGcTWInxqPMhPKVsEyVi8Cfl7UatJR55YWWx0Ry/o=": {
            "valueMac": {
              "type": "Buffer",
              "data": "druK4foJvwX+JEhAZtCpfPVcN4uYJVwzBBexna8Ku4k="
            }
          },
          "LpNTHM78jHXR5XZp4CG6ZJ7DeThX6yFVW2a25mfVxm4=": {
            "valueMac": {
              "type": "Buffer",
              "data": "BrvOiZXz8pTSS+AnCf11lsHfz06atFmf6WPaVMKY380="
            }
          }
        }
      },
      "regular": {
        "version": 3,
        "hash": {
          "type": "Buffer",
          "data": "VH8az02yb6ewF1ClSp/+zLkOy9XHfxWN9++GL2RVmu35Fso/5gxoTYXyYZnnvitVn/cAldkDkeM3xcJQTFebQPWOArEJGr9kNEqtMPPecDJWjiT7QJkJbofotM2E9JziwIPCvXHfDT9NiGYvjtf74zpfC5ufqMIobywM2wstG8Q="
        },
        "indexValueMap": {
          "7c1rmT53TmkqkjlmtZhGWXD1UbuwyK3iqkaQOjGhBkI=": {
            "valueMac": {
              "type": "Buffer",
              "data": "0wIw+6+o7rUrNTp4o/Gat99A/tB7xEXOa0xFpyzs1e0="
            }
          },
          "TXkRkEcd/4eK4Zs1Ve9bMxubNiDyE5QYHhGItPBpoh8=": {
            "valueMac": {
              "type": "Buffer",
              "data": "ee3ctqXxeHmFa8D+xeARPXGvTy4juVzVvV0Ma55mgUk="
            }
          }
        }
      },
      "regular_high": {
        "version": 2,
        "hash": {
          "type": "Buffer",
          "data": "7hqABpcrdVmwBFNqIzg+Hs8LtnO93S/pZrhxJ4EPRgfdMA3qc6I/qJSDzXmAyZ3j78Q88B85YmSTocaSN33EVIoaayZ80zkXi+dc85/ckC59HVpKTFgCvKAxCrlQ5fhnI5EUOd3zV1LVovh4pQvNk6ZmlUQAZt0uXXq5k6LrG94="
        },
        "indexValueMap": {
          "eT4M1TsgI4VFSZKBQYj+6BTTzt14x+fOXNWjSaGtqjg=": {
            "valueMac": {
              "type": "Buffer",
              "data": "4WqdlCkPu3pmhG00p6Sjn2NnFFU0Y288yF1KcbzMVfQ="
            }
          }
        }
      },
      "regular_low": {
        "version": 3,
        "hash": {
          "type": "Buffer",
          "data": "p0Vb6vIxpFOiD+KyZFOawsIpK26bxqTDPqqsZvqWcXG8986YV9wVqsN2nKutcdDBna3KXIXgyYwSZ3+McGHRq4v08PlN5XEYQgUF54OlQRhP79TfWK2r0ZRJ0QJhGuqcy5vMFArnUc71md58VGguFwtt/RcbuzQW7Hn794RDSv4="
        },
        "indexValueMap": {
          "27kxx2HrbLynWjdm1+PcEBY9bhwksVFGRyow225rpTs=": {
            "valueMac": {
              "type": "Buffer",
              "data": "Yobs07tpSozXUU1RA469tovNglQUCEY7/nP7C9amJSM="
            }
          },
          "Iwy/zAAo3Osm5Mw2kNhhgEM0RRBc8WeiNrFez8CWYKw=": {
            "valueMac": {
              "type": "Buffer",
              "data": "X8v++QOy15ze5NxAGQg6SjSFrBXFa8GlWwi2yxxBonI="
            }
          },
          "5XnoVgZVKIEnZhoNBOIHkFJzHW0/7Gys6lZzRgQJXvY=": {
            "valueMac": {
              "type": "Buffer",
              "data": "ThdICjR+TiVI4/alE3imr4TX2lRy1RoNIW+G8Jzj1y4="
            }
          }
        }
      }
    }
  }
}